fastGraph/__init__.py
fastGraph/__main__.py
fastGraph/graph.py
fastGraph/ngram.py
fastGraph-0.1.1.dist-info/LICENSE
fastGraph-0.1.1.dist-info/METADATA
fastGraph-0.1.1.dist-info/WHEEL
fastGraph-0.1.1.dist-info/entry_points.txt
fastGraph-0.1.1.dist-info/top_level.txt
fastGraph-0.1.1.dist-info/RECORD
