Metadata-Version: 2.1
Name: fastGraph
Version: 0.1.1
Summary: A fast and lightweight package designed for Graph Embedding.
Home-page: https://github.com/AngusKung/fastGraph
Author: Angus Kung
Author-email: angusthefrog@gmail.com
License: Apache-2.0
Keywords: fastGraph
Platform: UNKNOWN
Classifier: Development Status :: 2 - Pre-Alpha
Classifier: Intended Audience :: Developers
Classifier: Natural Language :: English
Classifier: Programming Language :: Python :: 3.6
Requires-Dist: argparse (>=1.3)
Requires-Dist: gensim (>=3.5.0)
Requires-Dist: numpy (>=1.13)
Requires-Dist: scipy (>=0.20.0)
Requires-Dist: scikit-learn (>=0.20)
Requires-Dist: six (>=1.8)
Requires-Dist: psutil (>=5.0.0)
Requires-Dist: pandas (>=0.23)
